llama_index/tools/vector_db/__init__.py
llama_index/tools/vector_db/base.py
llama_index_tools_vector_db-0.4.0.dist-info/METADATA
llama_index_tools_vector_db-0.4.0.dist-info/WHEEL
llama_index_tools_vector_db-0.4.0.dist-info/licenses/LICENSE
llama_index_tools_vector_db-0.4.0.dist-info/RECORD
